slave.py
overseer_slave-1.dist-info/LICENSE
overseer_slave-1.dist-info/METADATA
overseer_slave-1.dist-info/WHEEL
overseer_slave-1.dist-info/top_level.txt
overseer_slave-1.dist-info/RECORD
